bin-gray/b_g.v
module b_g(B, G);
    input  [3:0] B;
    output [3:0] G;


    assign G[3] = B[3];
    assign G[2] = B[3] ^ B[2];
    assign G[1] = B[2] ^ B[1];
    assign G[0] = B[1] ^ B[0];

endmodule

bin-gray/b_g_tb.v
`timescale 1ns / 1ns
`include "b_g.v"

module testbench;

    reg [3:0] B;
    wire [3:0] G;

    b_g uut (B,G);
        initial begin
        $dumpfile("b_g.vcd");
        $dumpvars(0,testbench);

        B = 4'b0000; #10;
        B = 4'b0001; #10;
        B = 4'b0010; #10;
        B = 4'b0011; #10;
        B = 4'b0100; #10;
        B = 4'b0101; #10;
        B = 4'b0110; #10;
        B = 4'b0111; #10;
        B = 4'b1000; #10;
        B = 4'b1001; #10;
        B = 4'b1010; #10;
        B = 4'b1011; #10;
        B = 4'b1100; #10;
        B = 4'b1101; #10;
        B = 4'b1110; #10;
        B = 4'b1111; #10;
        $finish;
    end
endmodule

bin-gray/b_g.vcd
$date
	Sat Jan 25 23:48:07 2025
$end
$version
	Icarus Verilog
$end
$timescale
	1ns
$end
$scope module testbench $end
$var wire 4 ! G [3:0] $end
$var reg 4 " B [3:0] $end
$scope module uut $end
$var wire 4 # B [3:0] $end
$var wire 4 $ G [3:0] $end
$upscope $end
$upscope $end
$enddefinitions $end
$comment Show the parameter values. $end
$dumpall
$end
#0
$dumpvars
b0 $
b0 #
b0 "
b0 !
$end
#10
b1 !
b1 $
b1 "
b1 #
#20
b11 !
b11 $
b10 "
b10 #
#30
b10 !
b10 $
b11 "
b11 #
#40
b110 !
b110 $
b100 "
b100 #
#50
b111 !
b111 $
b101 "
b101 #
#60
b101 !
b101 $
b110 "
b110 #
#70
b100 !
b100 $
b111 "
b111 #
#80
b1100 !
b1100 $
b1000 "
b1000 #
#90
b1101 !
b1101 $
b1001 "
b1001 #
#100
b1111 !
b1111 $
b1010 "
b1010 #
#110
b1110 !
b1110 $
b1011 "
b1011 #
#120
b1010 !
b1010 $
b1100 "
b1100 #
#130
b1011 !
b1011 $
b1101 "
b1101 #
#140
b1001 !
b1001 $
b1110 "
b1110 #
#150
b1000 !
b1000 $
b1111 "
b1111 #
