fsm/seq_detector.v
module seq_detector(x, clk, reset, y);
    input x, clk, reset;
    output reg y;

    // State definitions
    parameter S0 = 2'b00, S1 = 2'b01, S2 = 2'b10, S3 = 2'b11;
    reg [1:0] PS, NS;  // Present state and next state

    // State transition on clock and reset
    always @(posedge clk or posedge reset) begin
        if (reset) begin
            PS <= S0;
            y <= 1'b0;
        end else begin
            PS <= NS;
        end
    end

    // Next state logic and output logic
    always @(PS, x) begin
        case (PS)
            S0: begin
                y = 1'b0;
                NS = (x) ? S1 : S0;
            end
            S1: begin
                y = 1'b0;
                NS = (x) ? S2 : S0;
            end
            S2: begin
                y = 1'b0;
                NS = (x) ? S3 : S0;
            end
            S3: begin
                y = (x) ? 1'b1 : 1'b0; // Sequence detected
                NS = (x) ? S0 : S0;
            end
            default: begin
                y = 1'b0;
                NS = S0;
            end
        endcase
    end
endmodule

fsm/seq_detector_tb.v
`timescale 1ns / 1ps
`include "seq_detector.v"

module testbench;
    reg x, clk, reset;
    wire y;

    // Instantiate the DUT (Device Under Test)
    seq_detector uut (x, clk, reset, y);

    // Clock generation
    initial begin
        clk = 1'b0;
        forever #5 clk = ~clk;
    end

    // Test sequence
    initial begin
        $dumpfile("seq_detector.vcd");
        $dumpvars(0, testbench);

        // Initialize inputs
        x = 1'b0; reset = 1'b1;
        #15 reset = 1'b0;

        // Apply test sequence
        #12 x = 0; #10 x = 0; #10 x = 1; #10 x = 1;
        #10 x = 0; #10 x = 1; #10 x = 1; #10 x = 0;
        #10 x = 0; #10 x = 1; #10 x = 1; #10 x = 0;

        #10 $finish;
    end
endmodule

fsm/seq_detector.vcd
$date
	Sun Jan 26 11:27:37 2025
$end
$version
	Icarus Verilog
$end
$timescale
	1ps
$end
$scope module testbench $end
$var wire 1 ! y $end
$var reg 1 " clk $end
$var reg 1 # reset $end
$var reg 1 $ x $end
$scope module uut $end
$var wire 1 " clk $end
$var wire 1 # reset $end
$var wire 1 $ x $end
$var parameter 2 % S0 $end
$var parameter 2 & S1 $end
$var parameter 2 ' S2 $end
$var parameter 2 ( S3 $end
$var reg 2 ) NS [1:0] $end
$var reg 2 * PS [1:0] $end
$var reg 1 ! y $end
$upscope $end
$upscope $end
$enddefinitions $end
$comment Show the parameter values. $end
$dumpall
b11 (
b10 '
b1 &
b0 %
$end
#0
$dumpvars
b0 *
b0 )
0$
1#
0"
0!
$end
#5000
1"
#10000
0"
#15000
1"
0#
#20000
0"
#25000
1"
#30000
0"
#35000
1"
#40000
0"
#45000
1"
#47000
b1 )
1$
#50000
0"
#55000
b10 )
b1 *
1"
#60000
0"
#65000
b11 )
b10 *
1"
#67000
b0 )
0$
#70000
0"
#75000
b0 *
1"
#77000
b1 )
1$
#80000
0"
#85000
b10 )
b1 *
1"
#90000
0"
#95000
b11 )
b10 *
1"
#97000
b0 )
0$
#100000
0"
#105000
b0 *
1"
#110000
0"
#115000
1"
#117000
b1 )
1$
#120000
0"
#125000
b10 )
b1 *
1"
#130000
0"
#135000
b11 )
b10 *
1"
#137000
b0 )
0$
#140000
0"
#145000
b0 *
1"
